Metadata-Version: 2.4
Name: cursofiap-package-gothcoder
Version: 1.0.0
Summary: Descricao da sua lib cursofiap
Home-page: https://github.com/goth-coder/cursofiap
Author: Victor Santos
Author-email: vlsoexecutivo@gmail.com
License: MIT
Dynamic: author
Dynamic: author-email
Dynamic: description
Dynamic: description-content-type
Dynamic: home-page
Dynamic: license
Dynamic: summary
